{
  "Resources": {
    "lambdacodebucketE2D9333F": {
      "Type": "AWS::S3::Bucket",
      "Properties": {
        "BucketName": "bachelorarbeit-lambda-code-bucket"
      },
      "UpdateReplacePolicy": "Delete",
      "DeletionPolicy": "Delete",
      "Metadata": {
        "aws:cdk:path": "UtilsStack/lambda-code-bucket/Resource"
      }
    },
    "lambdacodebucketPolicy54CEFC01": {
      "Type": "AWS::S3::BucketPolicy",
      "Properties": {
        "Bucket": {
          "Ref": "lambdacodebucketE2D9333F"
        },
        "PolicyDocument": {
          "Statement": [
            {
              "Action": [
                "s3:GetBucket*",
                "s3:List*",
                "s3:DeleteObject*"
              ],
              "Effect": "Allow",
              "Principal": {
                "AWS": {
                  "Fn::GetAtt": [
                    "CustomS3AutoDeleteObjectsCustomResourceProviderRole3B1BD092",
                    "Arn"
                  ]
                }
              },
              "Resource": [
                {
                  "Fn::GetAtt": [
                    "lambdacodebucketE2D9333F",
                    "Arn"
                  ]
                },
                {
                  "Fn::Join": [
                    "",
                    [
                      {
                        "Fn::GetAtt": [
                          "lambdacodebucketE2D9333F",
                          "Arn"
                        ]
                      },
                      "/*"
                    ]
                  ]
                }
              ]
            }
          ],
          "Version": "2012-10-17"
        }
      },
      "Metadata": {
        "aws:cdk:path": "UtilsStack/lambda-code-bucket/Policy/Resource"
      }
    },
    "lambdacodebucketAutoDeleteObjectsCustomResourceDF111E0B": {
      "Type": "Custom::S3AutoDeleteObjects",
      "Properties": {
        "ServiceToken": {
          "Fn::GetAtt": [
            "CustomS3AutoDeleteObjectsCustomResourceProviderHandler9D90184F",
            "Arn"
          ]
        },
        "BucketName": {
          "Ref": "lambdacodebucketE2D9333F"
        }
      },
      "DependsOn": [
        "lambdacodebucketPolicy54CEFC01"
      ],
      "UpdateReplacePolicy": "Delete",
      "DeletionPolicy": "Delete",
      "Metadata": {
        "aws:cdk:path": "UtilsStack/lambda-code-bucket/AutoDeleteObjectsCustomResource/Default"
      }
    },
    "CustomS3AutoDeleteObjectsCustomResourceProviderRole3B1BD092": {
      "Type": "AWS::IAM::Role",
      "Properties": {
        "AssumeRolePolicyDocument": {
          "Version": "2012-10-17",
          "Statement": [
            {
              "Action": "sts:AssumeRole",
              "Effect": "Allow",
              "Principal": {
                "Service": "lambda.amazonaws.com"
              }
            }
          ]
        },
        "ManagedPolicyArns": [
          {
            "Fn::Sub": "arn:${AWS::Partition}:iam::aws:policy/service-role/AWSLambdaBasicExecutionRole"
          }
        ]
      },
      "Metadata": {
        "aws:cdk:path": "UtilsStack/Custom::S3AutoDeleteObjectsCustomResourceProvider/Role"
      }
    },
    "CustomS3AutoDeleteObjectsCustomResourceProviderHandler9D90184F": {
      "Type": "AWS::Lambda::Function",
      "Properties": {
        "Code": {
          "S3Bucket": {
            "Ref": "AssetParameters4cd61014b71160e8c66fe167e43710d5ba068b80b134e9bd84508cf9238b2392S3BucketBF7A7F3F"
          },
          "S3Key": {
            "Fn::Join": [
              "",
              [
                {
                  "Fn::Select": [
                    0,
                    {
                      "Fn::Split": [
                        "||",
                        {
                          "Ref": "AssetParameters4cd61014b71160e8c66fe167e43710d5ba068b80b134e9bd84508cf9238b2392S3VersionKeyFAF93626"
                        }
                      ]
                    }
                  ]
                },
                {
                  "Fn::Select": [
                    1,
                    {
                      "Fn::Split": [
                        "||",
                        {
                          "Ref": "AssetParameters4cd61014b71160e8c66fe167e43710d5ba068b80b134e9bd84508cf9238b2392S3VersionKeyFAF93626"
                        }
                      ]
                    }
                  ]
                }
              ]
            ]
          }
        },
        "Timeout": 900,
        "MemorySize": 128,
        "Handler": "__entrypoint__.handler",
        "Role": {
          "Fn::GetAtt": [
            "CustomS3AutoDeleteObjectsCustomResourceProviderRole3B1BD092",
            "Arn"
          ]
        },
        "Runtime": "nodejs12.x",
        "Description": {
          "Fn::Join": [
            "",
            [
              "Lambda function for auto-deleting objects in ",
              {
                "Ref": "lambdacodebucketE2D9333F"
              },
              " S3 bucket."
            ]
          ]
        }
      },
      "DependsOn": [
        "CustomS3AutoDeleteObjectsCustomResourceProviderRole3B1BD092"
      ],
      "Metadata": {
        "aws:cdk:path": "UtilsStack/Custom::S3AutoDeleteObjectsCustomResourceProvider/Handler"
      }
    },
    "deploysinglepageapplicationAwsCliLayer7BD25909": {
      "Type": "AWS::Lambda::LayerVersion",
      "Properties": {
        "Content": {
          "S3Bucket": {
            "Ref": "AssetParameterse9882ab123687399f934da0d45effe675ecc8ce13b40cb946f3e1d6141fe8d68S3BucketAEADE8C7"
          },
          "S3Key": {
            "Fn::Join": [
              "",
              [
                {
                  "Fn::Select": [
                    0,
                    {
                      "Fn::Split": [
                        "||",
                        {
                          "Ref": "AssetParameterse9882ab123687399f934da0d45effe675ecc8ce13b40cb946f3e1d6141fe8d68S3VersionKeyE415415F"
                        }
                      ]
                    }
                  ]
                },
                {
                  "Fn::Select": [
                    1,
                    {
                      "Fn::Split": [
                        "||",
                        {
                          "Ref": "AssetParameterse9882ab123687399f934da0d45effe675ecc8ce13b40cb946f3e1d6141fe8d68S3VersionKeyE415415F"
                        }
                      ]
                    }
                  ]
                }
              ]
            ]
          }
        },
        "Description": "/opt/awscli/aws"
      },
      "Metadata": {
        "aws:cdk:path": "UtilsStack/deploy-single-page-application/AwsCliLayer/Resource",
        "aws:asset:path": "asset.e9882ab123687399f934da0d45effe675ecc8ce13b40cb946f3e1d6141fe8d68.zip",
        "aws:asset:property": "Content"
      }
    },
    "deploysinglepageapplicationCustomResource52BEC3DC": {
      "Type": "Custom::CDKBucketDeployment",
      "Properties": {
        "ServiceToken": {
          "Fn::GetAtt": [
            "CustomCDKBucketDeployment8693BB64968944B69AAFB0CC9EB8756C81C01536",
            "Arn"
          ]
        },
        "SourceBucketNames": [
          {
            "Ref": "AssetParameters6a5268eefaf8c086f35971d0a1ce6fdcbbb37d8d9c4053a84f58c13d4240f7c3S3Bucket2126CCAD"
          }
        ],
        "SourceObjectKeys": [
          {
            "Fn::Join": [
              "",
              [
                {
                  "Fn::Select": [
                    0,
                    {
                      "Fn::Split": [
                        "||",
                        {
                          "Ref": "AssetParameters6a5268eefaf8c086f35971d0a1ce6fdcbbb37d8d9c4053a84f58c13d4240f7c3S3VersionKey6615CDC6"
                        }
                      ]
                    }
                  ]
                },
                {
                  "Fn::Select": [
                    1,
                    {
                      "Fn::Split": [
                        "||",
                        {
                          "Ref": "AssetParameters6a5268eefaf8c086f35971d0a1ce6fdcbbb37d8d9c4053a84f58c13d4240f7c3S3VersionKey6615CDC6"
                        }
                      ]
                    }
                  ]
                }
              ]
            ]
          }
        ],
        "DestinationBucketName": {
          "Ref": "lambdacodebucketE2D9333F"
        },
        "DestinationBucketKeyPrefix": "lambda/code",
        "Prune": true
      },
      "UpdateReplacePolicy": "Delete",
      "DeletionPolicy": "Delete",
      "Metadata": {
        "aws:cdk:path": "UtilsStack/deploy-single-page-application/CustomResource/Default"
      }
    },
    "CustomCDKBucketDeployment8693BB64968944B69AAFB0CC9EB8756CServiceRole89A01265": {
      "Type": "AWS::IAM::Role",
      "Properties": {
        "AssumeRolePolicyDocument": {
          "Statement": [
            {
              "Action": "sts:AssumeRole",
              "Effect": "Allow",
              "Principal": {
                "Service": "lambda.amazonaws.com"
              }
            }
          ],
          "Version": "2012-10-17"
        },
        "ManagedPolicyArns": [
          {
            "Fn::Join": [
              "",
              [
                "arn:",
                {
                  "Ref": "AWS::Partition"
                },
                ":iam::aws:policy/service-role/AWSLambdaBasicExecutionRole"
              ]
            ]
          }
        ]
      },
      "Metadata": {
        "aws:cdk:path": "UtilsStack/Custom::CDKBucketDeployment8693BB64968944B69AAFB0CC9EB8756C/ServiceRole/Resource"
      }
    },
    "CustomCDKBucketDeployment8693BB64968944B69AAFB0CC9EB8756CServiceRoleDefaultPolicy88902FDF": {
      "Type": "AWS::IAM::Policy",
      "Properties": {
        "PolicyDocument": {
          "Statement": [
            {
              "Action": [
                "s3:GetObject*",
                "s3:GetBucket*",
                "s3:List*"
              ],
              "Effect": "Allow",
              "Resource": [
                {
                  "Fn::Join": [
                    "",
                    [
                      "arn:",
                      {
                        "Ref": "AWS::Partition"
                      },
                      ":s3:::",
                      {
                        "Ref": "AssetParameters6a5268eefaf8c086f35971d0a1ce6fdcbbb37d8d9c4053a84f58c13d4240f7c3S3Bucket2126CCAD"
                      }
                    ]
                  ]
                },
                {
                  "Fn::Join": [
                    "",
                    [
                      "arn:",
                      {
                        "Ref": "AWS::Partition"
                      },
                      ":s3:::",
                      {
                        "Ref": "AssetParameters6a5268eefaf8c086f35971d0a1ce6fdcbbb37d8d9c4053a84f58c13d4240f7c3S3Bucket2126CCAD"
                      },
                      "/*"
                    ]
                  ]
                }
              ]
            },
            {
              "Action": [
                "s3:GetObject*",
                "s3:GetBucket*",
                "s3:List*",
                "s3:DeleteObject*",
                "s3:PutObject",
                "s3:Abort*"
              ],
              "Effect": "Allow",
              "Resource": [
                {
                  "Fn::GetAtt": [
                    "lambdacodebucketE2D9333F",
                    "Arn"
                  ]
                },
                {
                  "Fn::Join": [
                    "",
                    [
                      {
                        "Fn::GetAtt": [
                          "lambdacodebucketE2D9333F",
                          "Arn"
                        ]
                      },
                      "/*"
                    ]
                  ]
                }
              ]
            }
          ],
          "Version": "2012-10-17"
        },
        "PolicyName": "CustomCDKBucketDeployment8693BB64968944B69AAFB0CC9EB8756CServiceRoleDefaultPolicy88902FDF",
        "Roles": [
          {
            "Ref": "CustomCDKBucketDeployment8693BB64968944B69AAFB0CC9EB8756CServiceRole89A01265"
          }
        ]
      },
      "Metadata": {
        "aws:cdk:path": "UtilsStack/Custom::CDKBucketDeployment8693BB64968944B69AAFB0CC9EB8756C/ServiceRole/DefaultPolicy/Resource"
      }
    },
    "CustomCDKBucketDeployment8693BB64968944B69AAFB0CC9EB8756C81C01536": {
      "Type": "AWS::Lambda::Function",
      "Properties": {
        "Code": {
          "S3Bucket": {
            "Ref": "AssetParametersc24b999656e4fe6c609c31bae56a1cf4717a405619c3aa6ba1bc686b8c2c86cfS3Bucket55EFA30C"
          },
          "S3Key": {
            "Fn::Join": [
              "",
              [
                {
                  "Fn::Select": [
                    0,
                    {
                      "Fn::Split": [
                        "||",
                        {
                          "Ref": "AssetParametersc24b999656e4fe6c609c31bae56a1cf4717a405619c3aa6ba1bc686b8c2c86cfS3VersionKey60329B70"
                        }
                      ]
                    }
                  ]
                },
                {
                  "Fn::Select": [
                    1,
                    {
                      "Fn::Split": [
                        "||",
                        {
                          "Ref": "AssetParametersc24b999656e4fe6c609c31bae56a1cf4717a405619c3aa6ba1bc686b8c2c86cfS3VersionKey60329B70"
                        }
                      ]
                    }
                  ]
                }
              ]
            ]
          }
        },
        "Role": {
          "Fn::GetAtt": [
            "CustomCDKBucketDeployment8693BB64968944B69AAFB0CC9EB8756CServiceRole89A01265",
            "Arn"
          ]
        },
        "Handler": "index.handler",
        "Layers": [
          {
            "Ref": "deploysinglepageapplicationAwsCliLayer7BD25909"
          }
        ],
        "Runtime": "python3.6",
        "Timeout": 900
      },
      "DependsOn": [
        "CustomCDKBucketDeployment8693BB64968944B69AAFB0CC9EB8756CServiceRoleDefaultPolicy88902FDF",
        "CustomCDKBucketDeployment8693BB64968944B69AAFB0CC9EB8756CServiceRole89A01265"
      ],
      "Metadata": {
        "aws:cdk:path": "UtilsStack/Custom::CDKBucketDeployment8693BB64968944B69AAFB0CC9EB8756C/Resource",
        "aws:asset:path": "asset.c24b999656e4fe6c609c31bae56a1cf4717a405619c3aa6ba1bc686b8c2c86cf",
        "aws:asset:property": "Code"
      }
    },
    "CDKMetadata": {
      "Type": "AWS::CDK::Metadata",
      "Properties": {
        "Analytics": "v2:deflate64:H4sIAAAAAAAAA1WQu27DMAxFvyU7zdhNl25NHXTqYDhAd1ViA8V6FKKcwBD875XiPNqJV7wE76EabOoXrFev4syVVMM6SR8I0z4KOUDrHccwygjtyNHbntiPQRK03+6h/1ld8CetKMCWmWJec9DuUOY7EYSlmJ2/W3KC0lF7N0MhSLzB9DbKgWJxr2opnTdaTo/28p6BN1VS9GP8ZMlFXMzdvQGigDBeeGYwwn4pgSmv+RAThU8KnONhnzENRe/eRycLENxFHr3pGbSwmHpvlj8o9cF1JbqFVKYEVPkuaTRuz9wafcmcwXlFeOT1qanx6Rmb1ZG1rsLooraE/VJ/AeFDaZ6cAQAA"
      },
      "Metadata": {
        "aws:cdk:path": "UtilsStack/CDKMetadata/Default"
      },
      "Condition": "CDKMetadataAvailable"
    }
  },
  "Parameters": {
    "AssetParameters4cd61014b71160e8c66fe167e43710d5ba068b80b134e9bd84508cf9238b2392S3BucketBF7A7F3F": {
      "Type": "String",
      "Description": "S3 bucket for asset \"4cd61014b71160e8c66fe167e43710d5ba068b80b134e9bd84508cf9238b2392\""
    },
    "AssetParameters4cd61014b71160e8c66fe167e43710d5ba068b80b134e9bd84508cf9238b2392S3VersionKeyFAF93626": {
      "Type": "String",
      "Description": "S3 key for asset version \"4cd61014b71160e8c66fe167e43710d5ba068b80b134e9bd84508cf9238b2392\""
    },
    "AssetParameters4cd61014b71160e8c66fe167e43710d5ba068b80b134e9bd84508cf9238b2392ArtifactHashE56CD69A": {
      "Type": "String",
      "Description": "Artifact hash for asset \"4cd61014b71160e8c66fe167e43710d5ba068b80b134e9bd84508cf9238b2392\""
    },
    "AssetParameterse9882ab123687399f934da0d45effe675ecc8ce13b40cb946f3e1d6141fe8d68S3BucketAEADE8C7": {
      "Type": "String",
      "Description": "S3 bucket for asset \"e9882ab123687399f934da0d45effe675ecc8ce13b40cb946f3e1d6141fe8d68\""
    },
    "AssetParameterse9882ab123687399f934da0d45effe675ecc8ce13b40cb946f3e1d6141fe8d68S3VersionKeyE415415F": {
      "Type": "String",
      "Description": "S3 key for asset version \"e9882ab123687399f934da0d45effe675ecc8ce13b40cb946f3e1d6141fe8d68\""
    },
    "AssetParameterse9882ab123687399f934da0d45effe675ecc8ce13b40cb946f3e1d6141fe8d68ArtifactHashD9A515C3": {
      "Type": "String",
      "Description": "Artifact hash for asset \"e9882ab123687399f934da0d45effe675ecc8ce13b40cb946f3e1d6141fe8d68\""
    },
    "AssetParametersc24b999656e4fe6c609c31bae56a1cf4717a405619c3aa6ba1bc686b8c2c86cfS3Bucket55EFA30C": {
      "Type": "String",
      "Description": "S3 bucket for asset \"c24b999656e4fe6c609c31bae56a1cf4717a405619c3aa6ba1bc686b8c2c86cf\""
    },
    "AssetParametersc24b999656e4fe6c609c31bae56a1cf4717a405619c3aa6ba1bc686b8c2c86cfS3VersionKey60329B70": {
      "Type": "String",
      "Description": "S3 key for asset version \"c24b999656e4fe6c609c31bae56a1cf4717a405619c3aa6ba1bc686b8c2c86cf\""
    },
    "AssetParametersc24b999656e4fe6c609c31bae56a1cf4717a405619c3aa6ba1bc686b8c2c86cfArtifactHash85F58E48": {
      "Type": "String",
      "Description": "Artifact hash for asset \"c24b999656e4fe6c609c31bae56a1cf4717a405619c3aa6ba1bc686b8c2c86cf\""
    },
    "AssetParameters6a5268eefaf8c086f35971d0a1ce6fdcbbb37d8d9c4053a84f58c13d4240f7c3S3Bucket2126CCAD": {
      "Type": "String",
      "Description": "S3 bucket for asset \"6a5268eefaf8c086f35971d0a1ce6fdcbbb37d8d9c4053a84f58c13d4240f7c3\""
    },
    "AssetParameters6a5268eefaf8c086f35971d0a1ce6fdcbbb37d8d9c4053a84f58c13d4240f7c3S3VersionKey6615CDC6": {
      "Type": "String",
      "Description": "S3 key for asset version \"6a5268eefaf8c086f35971d0a1ce6fdcbbb37d8d9c4053a84f58c13d4240f7c3\""
    },
    "AssetParameters6a5268eefaf8c086f35971d0a1ce6fdcbbb37d8d9c4053a84f58c13d4240f7c3ArtifactHash7457051D": {
      "Type": "String",
      "Description": "Artifact hash for asset \"6a5268eefaf8c086f35971d0a1ce6fdcbbb37d8d9c4053a84f58c13d4240f7c3\""
    }
  },
  "Conditions": {
    "CDKMetadataAvailable": {
      "Fn::Or": [
        {
          "Fn::Or": [
            {
              "Fn::Equals": [
                {
                  "Ref": "AWS::Region"
                },
                "af-south-1"
              ]
            },
            {
              "Fn::Equals": [
                {
                  "Ref": "AWS::Region"
                },
                "ap-east-1"
              ]
            },
            {
              "Fn::Equals": [
                {
                  "Ref": "AWS::Region"
                },
                "ap-northeast-1"
              ]
            },
            {
              "Fn::Equals": [
                {
                  "Ref": "AWS::Region"
                },
                "ap-northeast-2"
              ]
            },
            {
              "Fn::Equals": [
                {
                  "Ref": "AWS::Region"
                },
                "ap-south-1"
              ]
            },
            {
              "Fn::Equals": [
                {
                  "Ref": "AWS::Region"
                },
                "ap-southeast-1"
              ]
            },
            {
              "Fn::Equals": [
                {
                  "Ref": "AWS::Region"
                },
                "ap-southeast-2"
              ]
            },
            {
              "Fn::Equals": [
                {
                  "Ref": "AWS::Region"
                },
                "ca-central-1"
              ]
            },
            {
              "Fn::Equals": [
                {
                  "Ref": "AWS::Region"
                },
                "cn-north-1"
              ]
            },
            {
              "Fn::Equals": [
                {
                  "Ref": "AWS::Region"
                },
                "cn-northwest-1"
              ]
            }
          ]
        },
        {
          "Fn::Or": [
            {
              "Fn::Equals": [
                {
                  "Ref": "AWS::Region"
                },
                "eu-central-1"
              ]
            },
            {
              "Fn::Equals": [
                {
                  "Ref": "AWS::Region"
                },
                "eu-north-1"
              ]
            },
            {
              "Fn::Equals": [
                {
                  "Ref": "AWS::Region"
                },
                "eu-south-1"
              ]
            },
            {
              "Fn::Equals": [
                {
                  "Ref": "AWS::Region"
                },
                "eu-west-1"
              ]
            },
            {
              "Fn::Equals": [
                {
                  "Ref": "AWS::Region"
                },
                "eu-west-2"
              ]
            },
            {
              "Fn::Equals": [
                {
                  "Ref": "AWS::Region"
                },
                "eu-west-3"
              ]
            },
            {
              "Fn::Equals": [
                {
                  "Ref": "AWS::Region"
                },
                "me-south-1"
              ]
            },
            {
              "Fn::Equals": [
                {
                  "Ref": "AWS::Region"
                },
                "sa-east-1"
              ]
            },
            {
              "Fn::Equals": [
                {
                  "Ref": "AWS::Region"
                },
                "us-east-1"
              ]
            },
            {
              "Fn::Equals": [
                {
                  "Ref": "AWS::Region"
                },
                "us-east-2"
              ]
            }
          ]
        },
        {
          "Fn::Or": [
            {
              "Fn::Equals": [
                {
                  "Ref": "AWS::Region"
                },
                "us-west-1"
              ]
            },
            {
              "Fn::Equals": [
                {
                  "Ref": "AWS::Region"
                },
                "us-west-2"
              ]
            }
          ]
        }
      ]
    }
  },
  "Outputs": {
    "ExportsOutputFnGetAttlambdacodebucketE2D9333FArn046927D9": {
      "Value": {
        "Fn::GetAtt": [
          "lambdacodebucketE2D9333F",
          "Arn"
        ]
      },
      "Export": {
        "Name": "bachelorarbeit-utils-stack:ExportsOutputFnGetAttlambdacodebucketE2D9333FArn046927D9"
      }
    }
  }
}